exoverses/__init__.py
exoverses/base/__init__.py
exoverses/base/disk.py
exoverses/base/planet.py
exoverses/base/star.py
exoverses/base/system.py
exoverses/base/universe.py
exoverses/data/mamajek_rhk.csv
exoverses/exosims/__init__.py
exoverses/exosims/planet.py
exoverses/exosims/star.py
exoverses/exosims/system.py
exoverses/exosims/universe.py
exoverses/exovista/__init__.py
exoverses/exovista/disk.py
exoverses/exovista/planet.py
exoverses/exovista/star.py
exoverses/exovista/system.py
exoverses/exovista/universe.py
exoverses/fit/__init__.py
exoverses/fit/planet.py
exoverses/fit/system.py
exoverses/util/__init__.py
exoverses/util/misc.py
exoverses-0.3.1.dist-info/METADATA
exoverses-0.3.1.dist-info/WHEEL
exoverses-0.3.1.dist-info/licenses/LICENSE
exoverses-0.3.1.dist-info/RECORD
