Metadata-Version: 2.4
Name: exoverses
Version: 0.3.1
Summary: A unified interface for the various tools that create universes for exoplanet simulations
Project-URL: Homepage, https://github.com/CoreySpohn/exoverses
Project-URL: Issues, https://github.com/CoreySpohn/exoverses/issues
Author-email: Corey Spohn <corey.a.spohn@nasa.gov>
License: MIT License
License-File: LICENSE
Classifier: License :: OSI Approved :: MIT License
Classifier: Programming Language :: Python :: 3
Requires-Dist: astropy
Requires-Dist: dill
Requires-Dist: keplertools
Requires-Dist: numpy
Requires-Dist: pandas
Requires-Dist: rebound>=4
Requires-Dist: scipy
Requires-Dist: tqdm>=4.56.0
Requires-Dist: xarray>=v2023.12
Provides-Extra: exosims
Requires-Dist: exosims; extra == 'exosims'
